{
  "timeline": {
    "round_2": {
      "turn_2": {
        "amount": 144567.0,
        "bid_time": "2015-10-30T14:44:25.843896+02:00",
        "bidder": "76e4d4785d8943d48c0cb1cf1d60c0db",
        "time": "2015-10-30T12:45:33.010136+00:00"
      },
      "turn_1": {
        "amount": 144626.0,
        "bid_time": "2015-10-30T14:42:41.557653+02:00",
        "bidder": "0629506c1a934ca087bfa317a12669f9",
        "time": "2015-10-30T12:43:33.015293+00:00"
      }
    },
    "round_3": {
      "turn_2": {
        "amount": 141162.0,
        "bid_time": "2015-10-30T14:50:39.538697+02:00",
        "bidder": "76e4d4785d8943d48c0cb1cf1d60c0db",
        "time": "2015-10-30T12:51:33.009124+00:00"
      },
      "turn_1": {
        "amount": 142100.0,
        "bid_time": "2015-10-30T14:48:03.085560+02:00",
        "bidder": "0629506c1a934ca087bfa317a12669f9",
        "time": "2015-10-30T12:49:33.011204+00:00"
      }
    },
    "round_1": {
      "turn_2": {
        "bidder": "76e4d4785d8943d48c0cb1cf1d60c0db",
        "time": "2015-10-30T12:39:33.007659+00:00"
      },
      "turn_1": {
        "bidder": "0629506c1a934ca087bfa317a12669f9",
        "time": "2015-10-30T12:37:33.010845+00:00"
      }
    },
    "results": {
      "bids": [
        {
          "bidder": "0629506c1a934ca087bfa317a12669f9",
          "amount": 142100.0,
          "identification": [
            {
              "contactPoint": {
                "url": "http://www.unk.ua",
                "telephone": "+380505757076",
                "name": "Общество с огрантченной отвественностью ОО Укрнафко",
                "email": "vladik19731@mail.ru"
              },
              "identifier": {
                "scheme": "UA-EDR",
                "id": "30427998",
                "legalName": "Общество с огрантченной отвественностью ОО Укрнафко"
              },
              "name": "Общество с огрантченной отвественностью ОО Укрнафко",
              "address": {
                "countryName": "Україна",
                "postalCode": "",
                "region": "",
                "streetAddress": "г.Харьков,ул.Б.Гончаровская,6",
                "locality": ""
              }
            }
          ],
          "time": "2015-10-30T14:48:03.085560+02:00"
        },
        {
          "bidder": "76e4d4785d8943d48c0cb1cf1d60c0db",
          "amount": 141162.0,
          "identification": [
            {
              "contactPoint": {
                "url": "http://YUKO.EU",
                "telephone": "+380504888808",
                "name": "ООО \"СП ЮКОЙЛ\"",
                "email": "gvardo@ukr.net"
              },
              "identifier": {
                "scheme": "UA-EDR",
                "id": "31852954",
                "legalName": "ООО \"СП ЮКОЙЛ\""
              },
              "name": "ООО \"СП ЮКОЙЛ\"",
              "address": {
                "countryName": "Україна",
                "postalCode": "",
                "region": "",
                "streetAddress": "Украина, 69014, г. Запорожье ул. Базовая 3\"А\"",
                "locality": ""
              }
            }
          ],
          "time": "2015-10-30T14:50:39.538697+02:00"
        }
      ],
      "time": "2015-10-30T12:51:37.195936+00:00"
    },
    "auction_start": {
      "initial_bids": [
        {
          "date": "2015-10-29T10:33:08.747096+02:00",
          "amount": 146626.0,
          "bidder": "0629506c1a934ca087bfa317a12669f9"
        },
        {
          "date": "2015-10-26T16:16:34.709485+02:00",
          "amount": 146567.64,
          "bidder": "76e4d4785d8943d48c0cb1cf1d60c0db"
        }
      ],
      "time": "2015-10-30T12:30:33.004795+00:00"
    }
  },
  "id": "0cfe026050204a63bbc28fd7ca431aa5",
  "tenderId": "UA-2015-10-21-000223"
}