{
  "timeline": {
    "round_2": {
      "turn_2": {
        "amount": 4779.0,
        "bid_time": "2015-12-03T11:29:09.401515+02:00",
        "bidder": "0ff42d3909f34b7c93422cdff25b6670",
        "time": "2015-12-03T09:29:39.009553+00:00"
      },
      "turn_1": {
        "amount": 4780.0,
        "bid_time": "2015-12-03T11:26:16.000428+02:00",
        "bidder": "0c9b369b14eb4be697b84a73becf97b4",
        "time": "2015-12-03T09:27:39.008978+00:00"
      }
    },
    "round_3": {
      "turn_2": {
        "amount": 4648.0,
        "bid_time": "2015-12-03T11:34:24.337154+02:00",
        "bidder": "0ff42d3909f34b7c93422cdff25b6670",
        "time": "2015-12-03T09:35:39.007224+00:00"
      },
      "turn_1": {
        "amount": 4649.0,
        "bid_time": "2015-12-03T11:32:28.304557+02:00",
        "bidder": "0c9b369b14eb4be697b84a73becf97b4",
        "time": "2015-12-03T09:33:39.007841+00:00"
      }
    },
    "round_1": {
      "turn_2": {
        "amount": 4861.0,
        "bid_time": "2015-12-03T11:22:26.543604+02:00",
        "bidder": "0ff42d3909f34b7c93422cdff25b6670",
        "time": "2015-12-03T09:23:39.026499+00:00"
      },
      "turn_1": {
        "amount": 4900.0,
        "bid_time": "2015-12-03T11:20:25.168458+02:00",
        "bidder": "0c9b369b14eb4be697b84a73becf97b4",
        "time": "2015-12-03T09:21:39.009721+00:00"
      }
    },
    "results": {
      "bids": [
        {
          "amount": 4649.0,
          "bidder": "0c9b369b14eb4be697b84a73becf97b4",
          "time": "2015-12-03T11:32:28.304557+02:00"
        },
        {
          "amount": 4648.0,
          "bidder": "0ff42d3909f34b7c93422cdff25b6670",
          "time": "2015-12-03T11:34:24.337154+02:00"
        }
      ],
      "time": "2015-12-03T09:35:39.035870+00:00"
    },
    "auction_start": {
      "initial_bids": [
        {
          "date": "2015-12-02T09:58:27.970806+02:00",
          "amount": 4950.0,
          "bidder": "0c9b369b14eb4be697b84a73becf97b4"
        },
        {
          "date": "2015-12-02T09:18:13.261341+02:00",
          "amount": 4911.0,
          "bidder": "0ff42d3909f34b7c93422cdff25b6670"
        }
      ],
      "time": "2015-12-03T09:14:39.004913+00:00"
    }
  },
  "id": "20ec612106f14f7a9c79fd784efce69d",
  "tenderId": "UA-2015-11-25-000096"
}