{
  "timeline": {
    "round_2": {
      "turn_2": {
        "bidder": "a8c413d891414e468080e4db67f56123",
        "time": "2015-11-20T12:25:20.007734+00:00"
      },
      "turn_1": {
        "bidder": "7c21cb39137149a0ac654ed93268ebbd",
        "time": "2015-11-20T12:23:20.009793+00:00"
      }
    },
    "round_3": {
      "turn_2": {
        "bidder": "a8c413d891414e468080e4db67f56123",
        "time": "2015-11-20T12:31:20.007776+00:00"
      },
      "turn_1": {
        "bidder": "7c21cb39137149a0ac654ed93268ebbd",
        "time": "2015-11-20T12:29:20.031536+00:00"
      }
    },
    "round_1": {
      "turn_2": {
        "bidder": "a8c413d891414e468080e4db67f56123",
        "time": "2015-11-20T12:19:20.009287+00:00"
      },
      "turn_1": {
        "bidder": "7c21cb39137149a0ac654ed93268ebbd",
        "time": "2015-11-20T12:17:20.013230+00:00"
      }
    },
    "results": {
      "bids": [
        {
          "bidder": "7c21cb39137149a0ac654ed93268ebbd",
          "amount": 61500.0,
          "identification": [
            {
              "contactPoint": {
                "url": "http://www.kvint.com.ua/",
                "faxNumber": "044-254-66-88",
                "telephone": "044-254-66-88",
                "name": "Сапон Олександр Вікторович",
                "email": "kvint@ukr.net"
              },
              "identifier": {
                "scheme": "UA-EDR",
                "id": "23503666",
                "legalName": "ПРИВАТНЕ АКЦІОНЕРНЕ ТОВАРИСТВО «ВЕГА»"
              },
              "name": "ПРИВАТНЕ АКЦІОНЕРНЕ ТОВАРИСТВО «ВЕГА»",
              "address": {
                "countryName": "Україна",
                "postalCode": "08110",
                "region": "Київська",
                "streetAddress": "вул.Шкільна, буд.30, с.Михайлівка-Рубежівка, Києво-Святошинський р-н,",
                "locality": "Київ"
              }
            }
          ],
          "time": "2015-11-18T15:50:37.622100+02:00"
        },
        {
          "bidder": "a8c413d891414e468080e4db67f56123",
          "amount": 53900.0,
          "identification": [
            {
              "contactPoint": {
                "telephone": "+380999299965, +380487886203, +380957542771, +380689397526",
                "name": "Игорь Лыков",
                "email": "agrolightod@gmail.com"
              },
              "identifier": {
                "scheme": "UA-EDR",
                "id": "2723111573",
                "legalName": "Агролайт"
              },
              "name": "Агролайт",
              "address": {
                "countryName": "Украина",
                "postalCode": "67667",
                "region": "Одесская",
                "streetAddress": "Тираспольское шоссе 7 км, 14, Одесса, Одесская область",
                "locality": "Одесса"
              }
            }
          ],
          "time": "2015-11-18T18:37:55.308874+02:00"
        }
      ],
      "time": "2015-11-20T12:31:23.038914+00:00"
    },
    "auction_start": {
      "initial_bids": [
        {
          "date": "2015-11-18T15:50:37.622100+02:00",
          "amount": 61500.0,
          "bidder": "7c21cb39137149a0ac654ed93268ebbd"
        },
        {
          "date": "2015-11-18T18:37:55.308874+02:00",
          "amount": 53900.0,
          "bidder": "a8c413d891414e468080e4db67f56123"
        }
      ],
      "time": "2015-11-20T12:10:20.006015+00:00"
    }
  },
  "id": "35f8a120ec8244d2942ca4f8c549d5da",
  "tenderId": "UA-2015-11-17-000009-b"
}