{
  "timeline": {
    "round_2": {
      "turn_6": {
        "amount": 9900.0,
        "bid_time": "2015-10-13T12:10:45.792740+03:00",
        "bidder": "4d848b75ed134e2eb08f7dd493d1ce5d",
        "time": "2015-10-13T09:12:16.013911+00:00"
      },
      "turn_7": {
        "amount": 9700.0,
        "bid_time": "2015-10-13T12:12:38.990402+03:00",
        "bidder": "7820adf9e668480dba62fc75c885d8c2",
        "time": "2015-10-13T09:14:16.014128+00:00"
      },
      "turn_4": {
        "amount": 9950.0,
        "bid_time": "2015-10-13T12:06:35.693304+03:00",
        "bidder": "184c3a39ce34487f907ab0f1eacf1148",
        "time": "2015-10-13T09:08:16.014895+00:00"
      },
      "turn_5": {
        "bidder": "8eb6ce6bfa5047b7a4c729b957c8e3bf",
        "time": "2015-10-13T09:10:16.009640+00:00"
      },
      "turn_2": {
        "bidder": "57e597f0dc094371b9a6488a988084bf",
        "time": "2015-10-13T09:04:16.010113+00:00"
      },
      "turn_3": {
        "bidder": "a756226cbe534c1ba79e8a74c76b5b1f",
        "time": "2015-10-13T09:06:16.013114+00:00"
      },
      "turn_1": {
        "bidder": "c14a41a0963d47a986032470ec6b75c3",
        "time": "2015-10-13T09:02:16.011104+00:00"
      }
    },
    "round_3": {
      "turn_6": {
        "bidder": "4d848b75ed134e2eb08f7dd493d1ce5d",
        "time": "2015-10-13T09:28:16.008893+00:00"
      },
      "turn_7": {
        "amount": 9400.0,
        "bid_time": "2015-10-13T12:28:39.137399+03:00",
        "bidder": "7820adf9e668480dba62fc75c885d8c2",
        "time": "2015-10-13T09:30:16.012537+00:00"
      },
      "turn_4": {
        "bidder": "8eb6ce6bfa5047b7a4c729b957c8e3bf",
        "time": "2015-10-13T09:24:16.012631+00:00"
      },
      "turn_5": {
        "amount": 9600.0,
        "bid_time": "2015-10-13T12:25:07.231423+03:00",
        "bidder": "184c3a39ce34487f907ab0f1eacf1148",
        "time": "2015-10-13T09:26:16.011879+00:00"
      },
      "turn_2": {
        "bidder": "57e597f0dc094371b9a6488a988084bf",
        "time": "2015-10-13T09:20:16.008995+00:00"
      },
      "turn_3": {
        "bidder": "a756226cbe534c1ba79e8a74c76b5b1f",
        "time": "2015-10-13T09:22:16.013115+00:00"
      },
      "turn_1": {
        "bidder": "c14a41a0963d47a986032470ec6b75c3",
        "time": "2015-10-13T09:18:16.009088+00:00"
      }
    },
    "round_1": {
      "turn_6": {
        "bidder": "8eb6ce6bfa5047b7a4c729b957c8e3bf",
        "time": "2015-10-13T08:56:16.011922+00:00"
      },
      "turn_7": {
        "bidder": "7820adf9e668480dba62fc75c885d8c2",
        "time": "2015-10-13T08:58:16.010892+00:00"
      },
      "turn_4": {
        "bidder": "184c3a39ce34487f907ab0f1eacf1148",
        "time": "2015-10-13T08:52:16.008933+00:00"
      },
      "turn_5": {
        "amount": 10200.0,
        "bid_time": "2015-10-13T11:52:56.179571+03:00",
        "bidder": "4d848b75ed134e2eb08f7dd493d1ce5d",
        "time": "2015-10-13T08:54:16.011678+00:00"
      },
      "turn_2": {
        "bidder": "57e597f0dc094371b9a6488a988084bf",
        "time": "2015-10-13T08:48:16.014211+00:00"
      },
      "turn_3": {
        "bidder": "a756226cbe534c1ba79e8a74c76b5b1f",
        "time": "2015-10-13T08:50:16.009397+00:00"
      },
      "turn_1": {
        "bidder": "c14a41a0963d47a986032470ec6b75c3",
        "time": "2015-10-13T08:46:16.006405+00:00"
      }
    },
    "results": {
      "bids": [
        {
          "bidder": "c14a41a0963d47a986032470ec6b75c3",
          "amount": 11000.0,
          "identification": [
            {
              "contactPoint": {
                "telephone": "+380665626484",
                "name": "Товариство з Обмеженою Відповідальністю  «ВЕКТОР-ЛЕД»",
                "email": "korchaga.slava@yandex.ru"
              },
              "identifier": {
                "scheme": "UA-EDR",
                "id": "39793116",
                "legalName": "Товариство з Обмеженою Відповідальністю  «ВЕКТОР-ЛЕД»"
              },
              "name": "Товариство з Обмеженою Відповідальністю  «ВЕКТОР-ЛЕД»",
              "address": {
                "countryName": "Україна",
                "postalCode": "",
                "region": "",
                "streetAddress": "01135, м. Київ, вул. Дмитрівська, буд. 71/1, оф. 1",
                "locality": ""
              }
            }
          ],
          "time": "2015-10-08T19:07:27.461922+03:00"
        },
        {
          "bidder": "57e597f0dc094371b9a6488a988084bf",
          "amount": 11000.0,
          "identification": [
            {
              "contactPoint": {
                "telephone": "+380617698912",
                "name": "Товариство з Обмеженою Відповідальністю \"НІК ЕНЕРГО\"",
                "email": "nik-energo@ukr.net"
              },
              "identifier": {
                "scheme": "UA-EDR",
                "id": "39385333",
                "legalName": "Товариство з Обмеженою Відповідальністю \"НІК ЕНЕРГО\""
              },
              "name": "Товариство з Обмеженою Відповідальністю \"НІК ЕНЕРГО\"",
              "address": {
                "countryName": "Україна",
                "postalCode": "",
                "region": "",
                "streetAddress": "м.Запоріжжя вул,Радгоспна 57б",
                "locality": ""
              }
            }
          ],
          "time": "2015-10-08T11:52:32.090836+03:00"
        },
        {
          "bidder": "a756226cbe534c1ba79e8a74c76b5b1f",
          "amount": 10995.01,
          "identification": [
            {
              "contactPoint": {
                "telephone": "+380675425553",
                "name": "Сергей Криводуб",
                "email": "electrifikator@ukr.net"
              },
              "identifier": {
                "scheme": "UA-EDR",
                "id": "36550495",
                "legalName": "ТОВ \"ТОВ ВКК Електрифікатор\""
              },
              "name": "ТОВ \"ТОВ ВКК Електрифікатор\"",
              "address": {
                "countryName": "Украина",
                "postalCode": "40000",
                "region": "Сумская",
                "streetAddress": "ул. Гагарина 9а оф. 224",
                "locality": "г. Суми"
              }
            }
          ],
          "time": "2015-10-08T15:54:33.559966+03:00"
        },
        {
          "bidder": "8eb6ce6bfa5047b7a4c729b957c8e3bf",
          "amount": 10375.0,
          "identification": [
            {
              "contactPoint": {
                "url": "http://intexgroop.kharkov.ua/",
                "telephone": "+380577665083",
                "name": "ТОВАРИСТВО З ОБМЕЖЕНОЮ ВІДПОВІДАЛЬНІСТЮ \"КОМПАНІЯ ІНТЕКС ГРУП\"",
                "email": "intexgroop@gmail.com"
              },
              "identifier": {
                "scheme": "UA-EDR",
                "id": "38631848",
                "legalName": "ТОВАРИСТВО З ОБМЕЖЕНОЮ ВІДПОВІДАЛЬНІСТЮ \"КОМПАНІЯ ІНТЕКС ГРУП\""
              },
              "name": "ТОВАРИСТВО З ОБМЕЖЕНОЮ ВІДПОВІДАЛЬНІСТЮ \"КОМПАНІЯ ІНТЕКС ГРУП\"",
              "address": {
                "countryName": "Україна",
                "postalCode": "",
                "region": "",
                "streetAddress": "пр-т Московський, б. 199, корпус Д-5, офіс 233, м. Харків, 61037",
                "locality": ""
              }
            }
          ],
          "time": "2015-10-08T12:06:30.686430+03:00"
        },
        {
          "bidder": "4d848b75ed134e2eb08f7dd493d1ce5d",
          "amount": 9900.0,
          "identification": [
            {
              "contactPoint": {
                "telephone": "+380671622872",
                "name": "Товариство з обмеженою відповідальністю \"ЕЛЕКТРОІМПУЛЬС\"",
                "email": "in@eimpuls.com.ua"
              },
              "identifier": {
                "scheme": "UA-EDR",
                "id": "35230100",
                "legalName": "Товариство з обмеженою відповідальністю \"ЕЛЕКТРОІМПУЛЬС\""
              },
              "name": "Товариство з обмеженою відповідальністю \"ЕЛЕКТРОІМПУЛЬС\"",
              "address": {
                "countryName": "Україна",
                "postalCode": "",
                "region": "",
                "streetAddress": "50086, Дніпропетровська обл., м. Кривий Ріг, Отто Брозовського, 72 В оф.215",
                "locality": ""
              }
            }
          ],
          "time": "2015-10-13T12:10:45.792740+03:00"
        },
        {
          "bidder": "184c3a39ce34487f907ab0f1eacf1148",
          "amount": 9600.0,
          "identification": [
            {
              "contactPoint": {
                "url": "http://www.svetonika.com.ua",
                "telephone": "+380504450280",
                "name": "Товариство з обмеженою відповідальністю \"Торговий дім Світоніка\"",
                "email": "bolyubash@svetonika.com.ua"
              },
              "identifier": {
                "scheme": "UA-EDR",
                "id": "37465610",
                "legalName": "Товариство з обмеженою відповідальністю \"Торговий дім Світоніка\""
              },
              "name": "Товариство з обмеженою відповідальністю \"Торговий дім Світоніка\"",
              "address": {
                "countryName": "Україна",
                "postalCode": "",
                "region": "",
                "streetAddress": "73000, Херсон, ул. Фонтанна, дом № 21, корпус 1, кв.102",
                "locality": ""
              }
            }
          ],
          "time": "2015-10-13T12:25:07.231423+03:00"
        },
        {
          "bidder": "7820adf9e668480dba62fc75c885d8c2",
          "amount": 9400.0,
          "identification": [
            {
              "contactPoint": {
                "telephone": "+380487773478",
                "name": "Товариство з обмеженою відповідальністю \"Грін Пауер\"",
                "email": "greenenergy@ukr.net"
              },
              "identifier": {
                "scheme": "UA-EDR",
                "id": "38226186",
                "legalName": "Товариство з обмеженою відповідальністю \"Грін Пауер\""
              },
              "name": "Товариство з обмеженою відповідальністю \"Грін Пауер\"",
              "address": {
                "countryName": "Україна",
                "postalCode": "",
                "region": "ОДЕССКАЯ ОБЛ.",
                "streetAddress": "65039, м. Одеса, вул. Артилерійська, буд. №11",
                "locality": "Одесса"
              }
            }
          ],
          "time": "2015-10-13T12:28:39.137399+03:00"
        }
      ],
      "time": "2015-10-13T09:30:26.013188+00:00"
    },
    "auction_start": {
      "initial_bids": [
        {
          "date": "2015-10-08T11:52:32.090836+03:00",
          "amount": 11000.0,
          "bidder": "57e597f0dc094371b9a6488a988084bf"
        },
        {
          "date": "2015-10-08T19:07:27.461922+03:00",
          "amount": 11000.0,
          "bidder": "c14a41a0963d47a986032470ec6b75c3"
        },
        {
          "date": "2015-10-08T15:54:33.559966+03:00",
          "amount": 10995.01,
          "bidder": "a756226cbe534c1ba79e8a74c76b5b1f"
        },
        {
          "date": "2015-10-08T09:16:56.585194+03:00",
          "amount": 10860.0,
          "bidder": "184c3a39ce34487f907ab0f1eacf1148"
        },
        {
          "date": "2015-10-09T16:16:27.089955+03:00",
          "amount": 10743.66,
          "bidder": "4d848b75ed134e2eb08f7dd493d1ce5d"
        },
        {
          "date": "2015-10-08T12:06:30.686430+03:00",
          "amount": 10375.0,
          "bidder": "8eb6ce6bfa5047b7a4c729b957c8e3bf"
        },
        {
          "date": "2015-10-09T17:30:58.571965+03:00",
          "amount": 10000.0,
          "bidder": "7820adf9e668480dba62fc75c885d8c2"
        }
      ],
      "time": "2015-10-13T08:39:16.002467+00:00"
    }
  },
  "id": "438f418db74b44cea903659678b6c196",
  "tenderId": "UA-2015-10-02-000240"
}