{
  "timeline": {
    "round_2": {
      "turn_2": {
        "bidder": "e8ca209a06684706a4aec6da51f31976",
        "time": "2015-10-12T08:58:10.005363+00:00"
      },
      "turn_3": {
        "bidder": "5864ad35590548d2b1c6a0856da3adcf",
        "time": "2015-10-12T09:00:10.012253+00:00"
      },
      "turn_1": {
        "amount": 3988.0,
        "bid_time": "2015-10-12T11:55:43.250171+03:00",
        "bidder": "806776e4728b4855b5e7eb9d385a8793",
        "time": "2015-10-12T08:56:10.007241+00:00"
      }
    },
    "round_3": {
      "turn_2": {
        "bidder": "806776e4728b4855b5e7eb9d385a8793",
        "time": "2015-10-12T09:06:10.009306+00:00"
      },
      "turn_3": {
        "bidder": "5864ad35590548d2b1c6a0856da3adcf",
        "time": "2015-10-12T09:08:10.007555+00:00"
      },
      "turn_1": {
        "bidder": "e8ca209a06684706a4aec6da51f31976",
        "time": "2015-10-12T09:04:10.011154+00:00"
      }
    },
    "round_1": {
      "turn_2": {
        "bidder": "806776e4728b4855b5e7eb9d385a8793",
        "time": "2015-10-12T08:50:10.006831+00:00"
      },
      "turn_3": {
        "bidder": "e8ca209a06684706a4aec6da51f31976",
        "time": "2015-10-12T08:52:10.007256+00:00"
      },
      "turn_1": {
        "amount": 3900.0,
        "bid_time": "2015-10-12T11:47:38.479209+03:00",
        "bidder": "5864ad35590548d2b1c6a0856da3adcf",
        "time": "2015-10-12T08:48:10.013876+00:00"
      }
    },
    "results": {
      "bids": [
        {
          "bidder": "e8ca209a06684706a4aec6da51f31976",
          "amount": 3997.75,
          "identification": [
            {
              "contactPoint": {
                "telephone": "+380671622872",
                "name": "Товариство з обмеженою відповідальністю \"ЕЛЕКТРОІМПУЛЬС\"",
                "email": "in@eimpuls.com.ua"
              },
              "identifier": {
                "scheme": "UA-EDR",
                "id": "35230100",
                "legalName": "Товариство з обмеженою відповідальністю \"ЕЛЕКТРОІМПУЛЬС\""
              },
              "name": "Товариство з обмеженою відповідальністю \"ЕЛЕКТРОІМПУЛЬС\"",
              "address": {
                "countryName": "Україна",
                "postalCode": "",
                "region": "",
                "streetAddress": "50086, Дніпропетровська обл., м. Кривий Ріг, Отто Брозовського, 72 В оф.215",
                "locality": ""
              }
            }
          ],
          "time": "2015-10-08T15:14:27.263388+03:00"
        },
        {
          "bidder": "806776e4728b4855b5e7eb9d385a8793",
          "amount": 3988.0,
          "identification": [
            {
              "contactPoint": {
                "telephone": "+380487773478",
                "name": "Товариство з обмеженою відповідальністю \"Грін Пауер\"",
                "email": "greenenergy@ukr.net"
              },
              "identifier": {
                "scheme": "UA-EDR",
                "id": "38226186",
                "legalName": "Товариство з обмеженою відповідальністю \"Грін Пауер\""
              },
              "name": "Товариство з обмеженою відповідальністю \"Грін Пауер\"",
              "address": {
                "countryName": "Україна",
                "postalCode": "",
                "region": "ОДЕССКАЯ ОБЛ.",
                "streetAddress": "65039, м. Одеса, вул. Артилерійська, буд. №11",
                "locality": "Одесса"
              }
            }
          ],
          "time": "2015-10-12T11:55:43.250171+03:00"
        },
        {
          "bidder": "5864ad35590548d2b1c6a0856da3adcf",
          "amount": 3900.0,
          "identification": [
            {
              "contactPoint": {
                "url": "http://tesi.com.ua",
                "telephone": "+380563705833",
                "name": "Товариство з обмеженою відповідальністю \"Теплові системи\"",
                "email": "gsa@tesi.com.ua"
              },
              "identifier": {
                "scheme": "UA-EDR",
                "id": "25009918",
                "legalName": "Товариство з обмеженою відповідальністю \"Теплові системи\""
              },
              "name": "Товариство з обмеженою відповідальністю \"Теплові системи\"",
              "address": {
                "countryName": "Україна",
                "postalCode": "",
                "region": "",
                "streetAddress": "49061, м. Дніпропетровськ, вул. Героїв Сталинграда, 23А",
                "locality": ""
              }
            }
          ],
          "time": "2015-10-12T11:47:38.479209+03:00"
        }
      ],
      "time": "2015-10-12T09:08:20.413376+00:00"
    },
    "auction_start": {
      "initial_bids": [
        {
          "date": "2015-10-06T11:35:52.833603+03:00",
          "amount": 4600.0,
          "bidder": "5864ad35590548d2b1c6a0856da3adcf"
        },
        {
          "date": "2015-10-07T22:14:35.661602+03:00",
          "amount": 4480.0,
          "bidder": "806776e4728b4855b5e7eb9d385a8793"
        },
        {
          "date": "2015-10-08T15:14:27.263388+03:00",
          "amount": 3997.75,
          "bidder": "e8ca209a06684706a4aec6da51f31976"
        }
      ],
      "time": "2015-10-12T08:41:10.002126+00:00"
    }
  },
  "id": "96da6c5f862644648689aa22a3082a55",
  "tenderId": "UA-2015-10-02-000279"
}