{
  "timeline": {
    "round_2": {
      "turn_4": {
        "bidder": "a327881a28ab4d88af764dc26d04ad0a",
        "time": "2015-07-31T08:55:00.032490+00:00"
      },
      "turn_5": {
        "bidder": "a7b2eeea752845c7890911ed48e265c8",
        "time": "2015-07-31T08:57:00.037867+00:00"
      },
      "turn_2": {
        "bidder": "4670a9c55e12442f9b01b843948036cc",
        "time": "2015-07-31T08:51:00.135490+00:00"
      },
      "turn_3": {
        "bidder": "b40565837547475495a86a74fb5f9b25",
        "time": "2015-07-31T08:53:00.025886+00:00"
      },
      "turn_1": {
        "bidder": "02d20ca5c1d24ec7ab6d85abcd4038f6",
        "time": "2015-07-31T08:49:00.023588+00:00"
      }
    },
    "round_3": {
      "turn_4": {
        "bidder": "a327881a28ab4d88af764dc26d04ad0a",
        "time": "2015-07-31T09:07:00.041489+00:00"
      },
      "turn_5": {
        "bidder": "a7b2eeea752845c7890911ed48e265c8",
        "time": "2015-07-31T09:09:00.022600+00:00"
      },
      "turn_2": {
        "bidder": "4670a9c55e12442f9b01b843948036cc",
        "time": "2015-07-31T09:03:00.023805+00:00"
      },
      "turn_3": {
        "bidder": "b40565837547475495a86a74fb5f9b25",
        "time": "2015-07-31T09:05:00.054386+00:00"
      },
      "turn_1": {
        "bidder": "02d20ca5c1d24ec7ab6d85abcd4038f6",
        "time": "2015-07-31T09:01:00.019760+00:00"
      }
    },
    "round_1": {
      "turn_4": {
        "bidder": "a327881a28ab4d88af764dc26d04ad0a",
        "time": "2015-07-31T08:43:00.039897+00:00"
      },
      "turn_5": {
        "bidder": "a7b2eeea752845c7890911ed48e265c8",
        "time": "2015-07-31T08:45:00.057521+00:00"
      },
      "turn_2": {
        "bidder": "4670a9c55e12442f9b01b843948036cc",
        "time": "2015-07-31T08:39:00.099581+00:00"
      },
      "turn_3": {
        "bidder": "b40565837547475495a86a74fb5f9b25",
        "time": "2015-07-31T08:41:00.060853+00:00"
      },
      "turn_1": {
        "bidder": "02d20ca5c1d24ec7ab6d85abcd4038f6",
        "time": "2015-07-31T08:37:00.073510+00:00"
      }
    },
    "results": {
      "bids": [
        {
          "bidder": "02d20ca5c1d24ec7ab6d85abcd4038f6",
          "amount": 5000.0,
          "identification": [
            {
              "contactPoint": {
                "url": "http://impera.com.ua",
                "telephone": "+380563704603",
                "name": "ООО Импера Групп",
                "email": "serg.impera@gmail.com"
              },
              "identifier": {
                "scheme": "UA-EDR",
                "id": "38677154",
                "legalName": "ООО Импера Групп"
              },
              "name": "ООО Импера Групп",
              "address": {
                "countryName": "Україна",
                "postalCode": "",
                "region": "",
                "streetAddress": "49098, г. Днепропетровск, ул. Белостоцкого, д. 159",
                "locality": ""
              }
            }
          ],
          "time": "2015-07-27T11:53:03.720050+03:00"
        },
        {
          "bidder": "4670a9c55e12442f9b01b843948036cc",
          "amount": 4900.0,
          "identification": [
            {
              "contactPoint": {
                "telephone": "+380442000578",
                "name": "Приватне Підприємство \"Купфер\"",
                "email": "bulahy@ukr.net"
              },
              "identifier": {
                "scheme": "UA-EDR",
                "id": "35920949",
                "legalName": "Приватне Підприємство \"Купфер\""
              },
              "name": "Приватне Підприємство \"Купфер\"",
              "address": {
                "countryName": "Україна",
                "postalCode": "",
                "region": "",
                "streetAddress": "01103 м. Київ, вул. Кіквідзе, буд. 13",
                "locality": ""
              }
            }
          ],
          "time": "2015-07-30T09:16:50.888847+03:00"
        },
        {
          "bidder": "b40565837547475495a86a74fb5f9b25",
          "amount": 4900.0,
          "identification": [
            {
              "contactPoint": {
                "telephone": "+380577164882",
                "name": "ООО \"Цветметпрокат\"",
                "email": "tsvetmetprokat@gmail.com"
              },
              "identifier": {
                "scheme": "UA-EDR",
                "id": "31152223",
                "legalName": "ООО \"Цветметпрокат\""
              },
              "name": "ООО \"Цветметпрокат\"",
              "address": {
                "countryName": "Україна",
                "postalCode": "",
                "region": "",
                "streetAddress": "61128,г.Харьков, пр.50-летия СССР,\r\nд.16, кв.396",
                "locality": ""
              }
            }
          ],
          "time": "2015-07-25T16:44:00.010240+03:00"
        },
        {
          "bidder": "a327881a28ab4d88af764dc26d04ad0a",
          "amount": 4822.2,
          "identification": [
            {
              "contactPoint": {
                "url": "http://evrotreyd.com",
                "telephone": "+380445011635",
                "name": "ЧАСНОЕ ПРЕДПРИЯТИЕ \"ЕВРОТРЕЙД\"",
                "email": "evrotreyd@voliacable.com"
              },
              "identifier": {
                "scheme": "UA-EDR",
                "id": "31870198",
                "legalName": "ЧАСНОЕ ПРЕДПРИЯТИЕ \"ЕВРОТРЕЙД\""
              },
              "name": "ЧАСНОЕ ПРЕДПРИЯТИЕ \"ЕВРОТРЕЙД\"",
              "address": {
                "countryName": "Україна",
                "postalCode": "",
                "region": "",
                "streetAddress": "08200, Киевская обл., г. Ирпень, ул.Фрунзе, 62",
                "locality": ""
              }
            }
          ],
          "time": "2015-07-29T11:38:10.084153+03:00"
        },
        {
          "bidder": "a7b2eeea752845c7890911ed48e265c8",
          "amount": 4514.0,
          "identification": [
            {
              "contactPoint": {
                "url": "http://www.e-tender.biz/",
                "telephone": "80675481000",
                "name": "Найда Володимирівна Алина",
                "email": "0675481000@ukr.net"
              },
              "identifier": {
                "scheme": "UA-EDR",
                "id": "38962562",
                "legalName": "Организация с ограниченной ответственностью Технолинии"
              },
              "name": "Организация с ограниченной ответственностью Технолинии",
              "address": {
                "countryName": "Україна",
                "postalCode": "03150",
                "region": "Київська",
                "streetAddress": "Красноармейская 139 оф. 351/1",
                "locality": ""
              }
            }
          ],
          "time": "2015-07-28T12:02:49.664363+03:00"
        }
      ],
      "time": "2015-07-31T09:09:01.779967+00:00"
    },
    "auction_start": {
      "initial_bids": [
        {
          "date": "2015-07-27T11:53:03.720050+03:00",
          "amount": 5000.0,
          "bidder": "02d20ca5c1d24ec7ab6d85abcd4038f6"
        },
        {
          "date": "2015-07-25T16:44:00.010240+03:00",
          "amount": 4900.0,
          "bidder": "b40565837547475495a86a74fb5f9b25"
        },
        {
          "date": "2015-07-30T09:16:50.888847+03:00",
          "amount": 4900.0,
          "bidder": "4670a9c55e12442f9b01b843948036cc"
        },
        {
          "date": "2015-07-29T11:38:10.084153+03:00",
          "amount": 4822.2,
          "bidder": "a327881a28ab4d88af764dc26d04ad0a"
        },
        {
          "date": "2015-07-28T12:02:49.664363+03:00",
          "amount": 4514.0,
          "bidder": "a7b2eeea752845c7890911ed48e265c8"
        }
      ],
      "time": "2015-07-31T08:30:00.010095+00:00"
    }
  },
  "id": "e41ba03cbd174d70be9bfca865b37149",
  "tenderId": "UA-2015-07-23-000032"
}